bluesky_queueserver/__init__.py
bluesky_queueserver/_version.py
bluesky_queueserver/manager/__init__.py
bluesky_queueserver/manager/annotation_decorator.py
bluesky_queueserver/manager/comms.py
bluesky_queueserver/manager/config.py
bluesky_queueserver/manager/conversions.py
bluesky_queueserver/manager/gen_lists.py
bluesky_queueserver/manager/json_rpc.py
bluesky_queueserver/manager/logging_setup.py
bluesky_queueserver/manager/manager.py
bluesky_queueserver/manager/output_streaming.py
bluesky_queueserver/manager/plan_monitoring.py
bluesky_queueserver/manager/plan_queue_ops.py
bluesky_queueserver/manager/profile_ops.py
bluesky_queueserver/manager/profile_tools.py
bluesky_queueserver/manager/qserver_cli.py
bluesky_queueserver/manager/start_manager.py
bluesky_queueserver/manager/task_results.py
bluesky_queueserver/manager/utils.py
bluesky_queueserver/manager/worker.py
bluesky_queueserver/manager/config_schemas/__init__.py
bluesky_queueserver/manager/config_schemas/config_schema.yml
bluesky_queueserver/manager/config_schemas/loading.py
bluesky_queueserver/manager/tests/__init__.py
bluesky_queueserver/manager/tests/common.py
bluesky_queueserver/manager/tests/conftest.py
bluesky_queueserver/manager/tests/plan_lists.py
bluesky_queueserver/manager/tests/spreadsheet_custom_functions.py
bluesky_queueserver/manager/tests/test_annotation_decorator.py
bluesky_queueserver/manager/tests/test_comms.py
bluesky_queueserver/manager/tests/test_config.py
bluesky_queueserver/manager/tests/test_console_monitor_cli.py
bluesky_queueserver/manager/tests/test_conversions.py
bluesky_queueserver/manager/tests/test_fixtures.py
bluesky_queueserver/manager/tests/test_gen_lists.py
bluesky_queueserver/manager/tests/test_info_streaming.py
bluesky_queueserver/manager/tests/test_ip_kernel_func.py
bluesky_queueserver/manager/tests/test_json_rpc.py
bluesky_queueserver/manager/tests/test_logging.py
bluesky_queueserver/manager/tests/test_manager.py
bluesky_queueserver/manager/tests/test_manager_options.py
bluesky_queueserver-0.0.24.dist-info/licenses/AUTHORS.rst
bluesky_queueserver-0.0.24.dist-info/licenses/LICENSE
bluesky_queueserver-0.0.24.dist-info/METADATA
bluesky_queueserver-0.0.24.dist-info/WHEEL
bluesky_queueserver-0.0.24.dist-info/entry_points.txt
bluesky_queueserver-0.0.24.dist-info/top_level.txt
bluesky_queueserver-0.0.24.dist-info/RECORD
