Metadata-Version: 2.4
Name: bluesky-queueserver
Version: 0.0.24
Summary: Server for queueing plans
Home-page: https://github.com/bluesky/bluesky-queueserver
Author: Brookhaven National Laboratory
Author-email: 
License: BSD (3-clause)
Classifier: Development Status :: 2 - Pre-Alpha
Classifier: Natural Language :: English
Classifier: Programming Language :: Python :: 3
Requires-Python: >=3.7
License-File: LICENSE
License-File: AUTHORS.rst
Requires-Dist: bluesky>=1.7.0
Requires-Dist: ipykernel
Requires-Dist: jsonschema
Requires-Dist: jupyter-client>=7.4.2
Requires-Dist: jupyter-console
Requires-Dist: numpydoc
Requires-Dist: openpyxl
Requires-Dist: ophyd
Requires-Dist: packaging
Requires-Dist: pydantic
Requires-Dist: python-multipart
Requires-Dist: pyyaml
Requires-Dist: pyzmq
Requires-Dist: redis[hiredis]
Requires-Dist: requests
Requires-Dist: typing-extensions; python_version < "3.8"
Dynamic: author
Dynamic: classifier
Dynamic: description
Dynamic: home-page
Dynamic: license
Dynamic: license-file
Dynamic: requires-dist
Dynamic: requires-python
Dynamic: summary
